invoice_ocr_mcp/__init__.py
invoice_ocr_mcp/config.py
invoice_ocr_mcp/server.py
invoice_ocr_mcp/modules/__init__.py
invoice_ocr_mcp/modules/batch_processor.py
invoice_ocr_mcp/modules/image_processor.py
invoice_ocr_mcp/modules/invoice_parser.py
invoice_ocr_mcp/modules/model_manager.py
invoice_ocr_mcp/modules/ocr_engine.py
invoice_ocr_mcp/modules/rapidocr_engine.py
invoice_ocr_mcp/modules/utils.py
invoice_ocr_mcp/modules/validators.py
invoice_ocr_mcp-1.0.4.dist-info/licenses/LICENSE
invoice_ocr_mcp-1.0.4.dist-info/METADATA
invoice_ocr_mcp-1.0.4.dist-info/WHEEL
invoice_ocr_mcp-1.0.4.dist-info/entry_points.txt
invoice_ocr_mcp-1.0.4.dist-info/top_level.txt
invoice_ocr_mcp-1.0.4.dist-info/RECORD
