Metadata-Version: 2.4
Name: invoice-ocr-mcp
Version: 1.0.4
Summary: 企业发票OCR识别MCP服务器 - 基于ModelScope的专业发票识别解决方案
Author-email: Invoice OCR Team <team@example.com>
License: MIT
Project-URL: Homepage, https://github.com/your-org/invoice-ocr-mcp
Project-URL: Documentation, https://github.com/your-org/invoice-ocr-mcp/docs
Project-URL: Repository, https://github.com/your-org/invoice-ocr-mcp.git
Project-URL: Issues, https://github.com/your-org/invoice-ocr-mcp/issues
Keywords: mcp,ocr,invoice,modelscope,ai
Classifier: Development Status :: 4 - Beta
Classifier: Intended Audience :: Developers
Classifier: License :: OSI Approved :: MIT License
Classifier: Programming Language :: Python :: 3
Classifier: Programming Language :: Python :: 3.8
Classifier: Programming Language :: Python :: 3.9
Classifier: Programming Language :: Python :: 3.10
Classifier: Programming Language :: Python :: 3.11
Classifier: Topic :: Software Development :: Libraries :: Python Modules
Classifier: Topic :: Scientific/Engineering :: Artificial Intelligence
Classifier: Topic :: Office/Business :: Financial
Requires-Python: >=3.8
License-File: LICENSE
Requires-Dist: mcp>=1.0.0
Requires-Dist: opencv-python>=4.8.0
Requires-Dist: Pillow>=10.0.0
Requires-Dist: numpy>=1.24.0
Requires-Dist: asyncio>=3.4.3
Requires-Dist: aiofiles>=23.2.0
Requires-Dist: aiohttp>=3.8.0
Requires-Dist: jsonschema>=4.17.0
Requires-Dist: pydantic>=2.0.0
Requires-Dist: python-dotenv>=1.0.0
Requires-Dist: PyYAML>=6.0.1
Requires-Dist: structlog>=23.1.0
Requires-Dist: rapidocr==3.2.0
Provides-Extra: dev
Requires-Dist: pytest>=7.4.0; extra == "dev"
Requires-Dist: pytest-asyncio>=0.21.0; extra == "dev"
Requires-Dist: pytest-mock>=3.11.0; extra == "dev"
Requires-Dist: pytest-cov>=4.1.0; extra == "dev"
Requires-Dist: black>=23.0.0; extra == "dev"
Requires-Dist: flake8>=6.0.0; extra == "dev"
Requires-Dist: isort>=5.12.0; extra == "dev"
Requires-Dist: mypy>=1.5.0; extra == "dev"
Provides-Extra: gpu
Requires-Dist: torch[cuda]>=2.0.0; extra == "gpu"
Requires-Dist: torchvision[cuda]>=0.15.0; extra == "gpu"
Provides-Extra: monitoring
Requires-Dist: prometheus-client>=0.17.0; extra == "monitoring"
Requires-Dist: redis>=4.6.0; extra == "monitoring"
Provides-Extra: performance
Requires-Dist: cachetools>=5.3.0; extra == "performance"
Requires-Dist: scikit-image>=0.21.0; extra == "performance"
Dynamic: license-file
